{
  "level": 1,
  "sizeX": 29,
  "sizeY": 18,
  "lives": 3,
  "ghostEatTime": 10,
  "map":"#############################/#*************#*************#/#*###*#*#####*#*#####*#*###*#/#*###*#*#####*#*#####*#*###*#/#+****#***************#****+#/#*#####*######*######*#####*#/#***************************#/#*#####*######X######*#####*#/#**###**#XXXXXBXXXXX#**###**#/#**###**#X###~~~###X#**###**#/#*#####*XX# Y I C #XX*#####*#/#*******#X#########X#*******#/#*#####*#XXXXX^XXXXX#*#####*#/#*****#*######*######*#*****#/#+###*#*******P*******#*###+#/#*###*#*#####*#*#####*#*###*#/#***************************#/#############################"
}